<configuration>
  <!-- ระบบไฟล์หลักของ HDFS -->
  <property>
    <name>fs.defaultFS</name>
    <value>hdfs://master:9000</value>
  </property>

  <!-- การตั้งค่าการอนุญาต proxy user -->
  <property>
    <name>hadoop.proxyuser.db_user.groups</name>
    <value>*</value>
  </property>
  <property>
    <name>hadoop.proxyuser.db_user.hosts</name>
    <value>*</value>
  </property>
  <property>
    <name>hadoop.proxyuser.server.hosts</name>
    <value>*</value>
  </property>
  <property>
    <name>hadoop.proxyuser.server.groups</name>
    <value>*</value>
  </property>
</configuration>